izda/System.py
izda/Write.py
izda/__init__.py
izda-1.0.5.dist-info/METADATA
izda-1.0.5.dist-info/WHEEL
izda-1.0.5.dist-info/top_level.txt
izda-1.0.5.dist-info/RECORD
